kfp/kubernetes/__init__.py
kfp/kubernetes/common.py
kfp/kubernetes/config_map.py
kfp/kubernetes/empty_dir.py
kfp/kubernetes/field.py
kfp/kubernetes/image.py
kfp/kubernetes/kubernetes_executor_config_pb2.py
kfp/kubernetes/node_affinity.py
kfp/kubernetes/node_selector.py
kfp/kubernetes/pod_metadata.py
kfp/kubernetes/secret.py
kfp/kubernetes/timeout.py
kfp/kubernetes/toleration.py
kfp/kubernetes/volume.py
kfp_kubernetes-2.15.2.dist-info/METADATA
kfp_kubernetes-2.15.2.dist-info/WHEEL
kfp_kubernetes-2.15.2.dist-info/top_level.txt
kfp_kubernetes-2.15.2.dist-info/RECORD
