Metadata-Version: 2.4
Name: kfp-kubernetes
Version: 2.15.2
Summary: Kubernetes platform configuration library and generated protos.
Home-page: https://github.com/kubeflow/pipelines
Author: google
Author-email: kubeflow-pipelines@google.com
License: Apache 2.0
Project-URL: Documentation, https://kfp-kubernetes.readthedocs.io/
Project-URL: Bug Tracker, https://github.com/kubeflow/pipelines/issues
Project-URL: Source, https://github.com/kubeflow/pipelines/tree/master/kubernetes_platform/python
Requires-Python: >=3.9.0
Requires-Dist: protobuf<7.0,>=6.31.1
Requires-Dist: kfp<3,>=2.14.5
Provides-Extra: dev
Requires-Dist: docformatter==1.4; extra == "dev"
Requires-Dist: isort==5.10.1; extra == "dev"
Requires-Dist: mypy==0.941; extra == "dev"
Requires-Dist: pre-commit==2.19.0; extra == "dev"
Requires-Dist: pycln==2.1.1; extra == "dev"
Requires-Dist: pytest==7.1.2; extra == "dev"
Requires-Dist: pytest-xdist==2.5.0; extra == "dev"
Requires-Dist: yapf==0.32.0; extra == "dev"
Dynamic: author
Dynamic: author-email
Dynamic: description
Dynamic: description-content-type
Dynamic: home-page
Dynamic: license
Dynamic: project-url
Dynamic: provides-extra
Dynamic: requires-dist
Dynamic: requires-python
Dynamic: summary
